[{"line":2,"uri":"file:src/main/resources/features/Payment.feature","id":"payment-functionality-test","keyword":"Feature","name":"Payment Functionality Test","description":"","elements":[{"start_timestamp":"2025-12-05T03:15:04.115Z","line":3,"id":"payment-functionality-test;payment-should-be-successful-when-add-to-cart-and-checkout","type":"scenario","keyword":"Scenario","name":"Payment should be successful when add to cart and checkout","description":"","steps":[{"keyword":"Given ","line":5,"match":{"location":"com.guru99.steps.StepDef.open_any_browser()"},"name":"Open any browser","result":{"duration":7158242400,"status":"passed"}},{"keyword":"And ","line":6,"match":{"location":"com.guru99.steps.StepDef.go_to_application_link()"},"name":"Go to application link","result":{"duration":3152577000,"status":"passed"}},{"keyword":"When ","line":7,"match":{"location":"com.guru99.steps.StepDef.select_product_quantity_to_four()"},"name":"Select product quantity to four","result":{"duration":3188842500,"status":"passed"}},{"keyword":"And ","line":8,"match":{"location":"com.guru99.steps.StepDef.click_buy_now()"},"name":"Click buy now","result":{"duration":548044500,"status":"passed"}},{"keyword":"And ","line":9,"match":{"location":"com.guru99.steps.StepDef.add_credit_card_information()"},"name":"Add Credit card information","result":{"duration":571411300,"status":"passed"}},{"keyword":"And ","line":10,"match":{"location":"com.guru99.steps.StepDef.click_submit_order()"},"name":"Click submit order","result":{"duration":460620400,"status":"passed"}},{"keyword":"Then ","line":11,"match":{"location":"com.guru99.steps.StepDef.order_should_be_successful_and_order_id_should_be_generated()"},"name":"Order should be successful and order id should be generated","result":{"duration":320186300,"status":"passed"}}],"tags":[{"name":"@Smoke"},{"name":"@Functional"},{"name":"@Regression"}]}],"tags":[{"name":"@Smoke","type":"Tag","location":{"line":1,"column":1}},{"name":"@Functional","type":"Tag","location":{"line":1,"column":8}},{"name":"@Regression","type":"Tag","location":{"line":1,"column":20}}]}]